ai_infra_cost_estimator/__init__.py
ai_infra_cost_estimator/cli.py
ai_infra_cost_estimator/calculator/__init__.py
ai_infra_cost_estimator/calculator/infra.py
ai_infra_cost_estimator/calculator/llm.py
ai_infra_cost_estimator/calculator/scaling.py
ai_infra_cost_estimator/pricing/__init__.py
ai_infra_cost_estimator/pricing/models.json
ai_infra_cost_estimator/report/__init__.py
ai_infra_cost_estimator/report/json_report.py
ai_infra_cost_estimator/report/markdown.py
ai_infra_cost_estimator-1.0.1.dist-info/licenses/LICENSE
ai_infra_cost_estimator-1.0.1.dist-info/METADATA
ai_infra_cost_estimator-1.0.1.dist-info/WHEEL
ai_infra_cost_estimator-1.0.1.dist-info/entry_points.txt
ai_infra_cost_estimator-1.0.1.dist-info/top_level.txt
ai_infra_cost_estimator-1.0.1.dist-info/RECORD
