Metadata-Version: 2.4
Name: ai-infra-cost-estimator
Version: 1.0.1
Summary: Estimate real-world AI + cloud infrastructure costs for LLM applications
Home-page: https://github.com/MindTheInfraAI/AI_Infra_Cost_Estimator
Author: MindTheInfraAI
Author-email: MindTheInfraAI <info@mindtheinfra.ai>
Maintainer-email: MindTheInfraAI <info@mindtheinfra.ai>
License: MIT
Project-URL: Homepage, https://github.com/MindTheInfraAI/AI_Infra_Cost_Estimator
Project-URL: Documentation, https://github.com/MindTheInfraAI/AI_Infra_Cost_Estimator#readme
Project-URL: Repository, https://github.com/MindTheInfraAI/AI_Infra_Cost_Estimator.git
Project-URL: Issues, https://github.com/MindTheInfraAI/AI_Infra_Cost_Estimator/issues
Keywords: ai,llm,cost-estimation,infrastructure,cloud,openai,anthropic,gpt,claude,pricing,budget
Classifier: Development Status :: 4 - Beta
Classifier: Intended Audience :: Developers
Classifier: Intended Audience :: System Administrators
Classifier: Intended Audience :: Financial and Insurance Industry
Classifier: License :: OSI Approved :: MIT License
Classifier: Operating System :: OS Independent
Classifier: Programming Language :: Python :: 3
Classifier: Programming Language :: Python :: 3.9
Classifier: Programming Language :: Python :: 3.10
Classifier: Programming Language :: Python :: 3.11
Classifier: Programming Language :: Python :: 3.12
Classifier: Topic :: Office/Business :: Financial
Classifier: Topic :: Software Development :: Libraries :: Python Modules
Classifier: Topic :: System :: Systems Administration
Requires-Python: >=3.9
License-File: LICENSE
Requires-Dist: pyyaml>=6.0
Provides-Extra: dev
Requires-Dist: pytest>=7.0; extra == "dev"
Requires-Dist: pytest-cov>=4.0; extra == "dev"
Requires-Dist: black>=23.0; extra == "dev"
Requires-Dist: isort>=5.0; extra == "dev"
Requires-Dist: mypy>=1.0; extra == "dev"
Requires-Dist: flake8>=6.0; extra == "dev"
Dynamic: author
Dynamic: home-page
Dynamic: license-file
Dynamic: requires-python
